django_torque-0.8.3.dist-info/licenses/LICENSE.md
torque/__init__.py
torque/apps.py
torque/explore_cache.py
torque/models.py
torque/signals.py
torque/urls.py
torque/utils.py
torque/version.py
torque/views.py
torque/cache_rebuilder/__init__.py
torque/cache_rebuilder/apps.py
torque/cache_rebuilder/background.py
torque/management/commands/__init__.py
torque/management/commands/remove_unattached.py
torque/management/commands/run_cache_rebuilder.py
torque/migrations/0001_initial.py
torque/migrations/0002_auto_20210321_1604.py
torque/migrations/0003_auto_20210321_1725.py
torque/migrations/0005_auto_20210323_1303.py
torque/migrations/0006_auto_20210323_1623.py
torque/migrations/0007_auto_20210406_1738.py
torque/migrations/0008_auto_20210406_1909.py
torque/migrations/0009_sheetconfig_search_cache_dirty.py
torque/migrations/0010_tableofcontentscache.py
torque/migrations/0011_auto_20210416_1739.py
torque/migrations/0012_searchcacherow_dirty.py
torque/migrations/0013_spreadsheet_last_updated.py
torque/migrations/0014_tableofcontentscache_rendered_html.py
torque/migrations/0015_remove_tableofcontentscache_rendered_data.py
torque/migrations/0016_auto_20210721_1444.py
torque/migrations/0017_auto_20210721_1621.py
torque/migrations/0018_delete_permissiongroup.py
torque/migrations/0019_auto_20210721_1720.py
torque/migrations/0020_tableofcontents_raw.py
torque/migrations/0021_remove_column_type.py
torque/migrations/0022_auto_20210905_1430.py
torque/migrations/0023_auto_20210905_1454.py
torque/migrations/0024_auto_20210905_1535.py
torque/migrations/0025_auto_20210905_1624.py
torque/migrations/0026_auto_20210905_1638.py
torque/migrations/0027_auto_20210905_1642.py
torque/migrations/0028_auto_20210905_1659.py
torque/migrations/0029_auto_20210905_1716.py
torque/migrations/0030_auto_20210927_1304.py
torque/migrations/0031_auto_20210930_1328.py
torque/migrations/0032_searchcachedocument_filtered_data.py
torque/migrations/0033_csvspecification.py
torque/migrations/0034_auto_20220209_1209.py
torque/migrations/0035_template_in_config.py
django_torque-0.8.3.dist-info/METADATA
django_torque-0.8.3.dist-info/WHEEL
django_torque-0.8.3.dist-info/top_level.txt
django_torque-0.8.3.dist-info/RECORD
