Metadata-Version: 2.4
Name: django-torque
Version: 0.8.3
Summary: django app for torque
Home-page: https://code.librehq.com/ots/mediawiki/torque
Author: Open Tech Strategies, LLC
Author-email: frankduncan@opentechstrategies.com
Classifier: Programming Language :: Python :: 3
Classifier: License :: OSI Approved :: GNU Affero General Public License v3
Classifier: Operating System :: OS Independent
License-File: LICENSE.md
Requires-Dist: mwclient
Requires-Dist: python-magic
Requires-Dist: jinja2
Requires-Dist: werkzeug
Requires-Dist: django
Requires-Dist: psycopg2-binary
Requires-Dist: orjson
Requires-Dist: xlsxwriter
Provides-Extra: dev
Requires-Dist: pytest; extra == "dev"
Requires-Dist: pytest-django; extra == "dev"
Requires-Dist: pytest-cov; extra == "dev"
Dynamic: author
Dynamic: author-email
Dynamic: classifier
Dynamic: description
Dynamic: description-content-type
Dynamic: home-page
Dynamic: license-file
Dynamic: provides-extra
Dynamic: requires-dist
Dynamic: summary
